app/__init__.py
app/__main__.py
app/context.py
app/loader.py
app/toskose.py
app/common/__init__.py
app/common/commons.py
app/common/constants.py
app/common/exception.py
app/common/logging.py
app/configuration/__init__.py
app/configuration/validation.py
app/docker/__init__.py
app/docker/compose.py
app/docker/manager.py
app/gui/__init__.py
app/gui/cli.py
app/gui/effects.py
app/supervisord/__init__.py
app/supervisord/configurator.py
app/tosca/__init__.py
app/tosca/parser.py
app/tosca/protocol_helper.py
app/tosca/validator.py
app/tosca/model/__init__.py
app/tosca/model/artifacts.py
app/tosca/model/nodes.py
app/tosca/model/protocol.py
app/tosca/model/relationships.py
app/tosca/model/template.py
tests/__init__.py
tests/commons.py
tests/conftest.py
tests/helpers.py
tests/test_composer.py
tests/test_configurator.py
tests/test_context_generation.py
tests/test_docker_manager.py
tests/test_supervisord_configurator.py
tests/test_tosca_parser.py
tests/test_tosca_validation.py
tests/test_toskose_model.py
tests/test_toskoserizator.py
toskose-0.1.0.dist-info/METADATA
toskose-0.1.0.dist-info/WHEEL
toskose-0.1.0.dist-info/entry_points.txt
toskose-0.1.0.dist-info/top_level.txt
toskose-0.1.0.dist-info/RECORD
